openscriber/__init__.py
openscriber/openscriber.py
tests/__init__.py
openscriber-0.1.0.dist-info/LICENSE
openscriber-0.1.0.dist-info/METADATA
openscriber-0.1.0.dist-info/WHEEL
openscriber-0.1.0.dist-info/entry_points.txt
openscriber-0.1.0.dist-info/top_level.txt
openscriber-0.1.0.dist-info/RECORD
